LICENSE
MANIFEST.in
README.md
quicktest.py
settings_test.py
setup.py
django_vkontakte_polls.egg-info/PKG-INFO
django_vkontakte_polls.egg-info/SOURCES.txt
django_vkontakte_polls.egg-info/dependency_links.txt
django_vkontakte_polls.egg-info/not-zip-safe
django_vkontakte_polls.egg-info/requires.txt
django_vkontakte_polls.egg-info/top_level.txt
vkontakte_polls/__init__.py
vkontakte_polls/__init__.pyc
vkontakte_polls/admin.py
vkontakte_polls/admin.pyc
vkontakte_polls/factories.py
vkontakte_polls/factories.pyc
vkontakte_polls/models.py
vkontakte_polls/models.pyc
vkontakte_polls/signals.py
vkontakte_polls/signals.pyc
vkontakte_polls/tests.py
vkontakte_polls/tests.pyc
vkontakte_polls/migrations/0001_initial.py
vkontakte_polls/migrations/0001_initial.pyc
vkontakte_polls/migrations/0002_auto.py
vkontakte_polls/migrations/0002_auto.pyc
vkontakte_polls/migrations/__init__.py
vkontakte_polls/migrations/__init__.pyc