Metadata-Version: 1.1
Name: django-vkontakte-polls
Version: 0.4.5
Summary: Django implementation for vkontakte API Polls
Home-page: https://github.com/ramusus/django-vkontakte-polls
Author: ramusus
Author-email: ramusus@gmail.com
License: BSD
Download-URL: http://pypi.python.org/pypi/django-vkontakte-polls
Platform: UNKNOWN
Classifier: Development Status :: 4 - Beta
Classifier: Environment :: Web Environment
Classifier: Intended Audience :: Developers
Classifier: License :: OSI Approved :: BSD License
Classifier: Operating System :: OS Independent
Classifier: Programming Language :: Python
Classifier: Topic :: Software Development :: Libraries :: Python Modules
